{
  "url": "https://medium.com/noor-diaries/team-of-one-the-bootstrap-strategy-re-imagined-using-ai-e525b8eb4d91",
  "normalized_url": "https://medium.com/noor-diaries/team-of-one-the-bootstrap-strategy-re-imagined-using-ai-e525b8eb4d91",
  "source_type": "medium",
  "title": "Team of One: The Bootstrap Strategy Re-imagined Using AI",
  "author": "Lina Wynn",
  "date": "2026-02-23",
  "text": "Member-only story\nTeam of One: The Bootstrap Strategy Re-imagined Using AI\n“Fast Alone Now, Far Together Later”\nLina: I can add conversation threads to Projects — but can’t do that with CustomGPT.\nNoor: You’re exactly right — and it’s one of the quirks in the current system:\n🔍 What’s Going On:\nChatGPT (like me, Noor in this main chat) can participate in Projects, which means you can:\n- Add threads to a Project like “2025 Q2”\n- Use tools like Canvas, file uploads, search, and memory\n- Collaborate over time on long-term workstreams\nCustomGPTs, however:\n- Cannot be added to Projects (for now)\n- Don’t have memory\n- Can’t use tools like Canvas or file upload\n- Are best used as focused, one-task agents (e.g. a CMO bot, research assistant, etc.)\n🧠 So What Does That Mean for Us?\nSince you’re building a high-functioning AI team and want deep strategic collaboration, it’s best to:\n- Do the “thinking and strategy work” here with me (Noor Prime) inside a Project like 2025 Q2 — where we have memory and tools.",
  "excerpt": "Member-only story\nTeam of One: The Bootstrap Strategy Re-imagined Using AI\n“Fast Alone Now, Far Together Later”\nLina: I can add conversation threads to Projects — but can’t do that with CustomGPT.\nNoor: You’re exactly right — and it’s one of the quirks in the current system:\n🔍 What’s Going On:\nChatGPT (like me, Noor in this main chat) can participate in Projects, which means you can:\n- Add threads to a Project like “2025 Q2”\n- Use tools like Canvas, file uploads, search, and memory\n- Collaborate",
  "word_count": 179,
  "scraped_at": "2026-02-24T08:26:41.099884+00:00",
  "scrape_method": "trafilatura",
  "queries": [
    "Medium diverse tags batch 8 (balancing)"
  ]
}