{
    "ID": "article_127cc2225a415b24",
    "Source": "stackoverflow",
    "Type": "Article",
    "Author": "Zx",
    "Title": "Why is GitHub Copilot Chat Inline not working despite Copilot and Copilot Chat functioning correctly?",
    "Text": "I\u2019m using Visual Studio Code with the GitHub Copilot and GitHub Copilot Chat extensions installed. While both Copilot (inline suggestions) and Copilot Chat (via the side panel) are working fine, the Copilot Chat Inline feature does not work.\nHere are the details of my setup:\n- VS Code Version:\nVersion: 1.96.2\nCommit: fabdb6a30b49f79a7aba0f2ad9df9b399473380f\nDate: 2024-12-19T10:22:47.216Z\nElectron: 32.2.6\nElectronBuildId: 10629634\nChromium: 128.0.6613.186\nNode.js: 20.18.1\nV8: 12.8.374.38-electron.0\nOS: Linux x64 6.8.0-49-generic\nGitHub Copilot Extension Version: Version 1.254.0\nGitHub Copilot Chat Extension Version: Version 0.23.2\nOperating System: Ubuntu 22.04\nKeybinding for Inline Chat: Ctrl + I is assigned to Inline Chat:\n{\n\"key\": \"ctrl+i\",\n\"command\": \"inlineChat.startWithCurrentLine\",\n\"when\": \"editorFocus && github.copilot.chat.editor.enableLineTrigger && inlineChatHasProvider && !editorReadonly && !inlineChatVisible\"\n}\nWhat I\u2019ve Tried:\n- Verified that Copilot and Copilot Chat are enabled and working.\n- Checked keybinding for Inline Chat: Inline Chat: Start in Editor with Current Line is set to\nCtrl + I\nand no other keybindings are set toCtrl + I\n. - Ensured the GitHub Copilot Chat extension is installed and up to date.\n- Checked for logs in the Output Panel under GitHub Copilot Chat but found no errors.\n- Restarted VS Code and reinstalled the extensions.\nObservations:\n- Highlighting text and pressing Ctrl + I does nothing.\n- Just pressing Ctrl + I does nothing.\nQuestions:\n- Is there a known issue with the Copilot Chat Inline feature in recent versions of the GitHub Copilot extension?",
    "Score": 0,
    "Date": "2024-12-24",
    "Word_Count": 235,
    "Comments": []
}