{
    "ID": "article_960bad8a3b563144",
    "Source": "medium",
    "Type": "Article",
    "Author": "Manpreet Singh",
    "Title": "Is AI Actually Dead? I Spent Two Days Finding Out..",
    "Text": "Member-only story\nIs AI Actually Dead? I Spent Two Days Finding Out..\nThe AI hype bubble is deflating. But that doesn\u2019t mean AI is dead.\nOkay so I woke up Monday to like 47 messages in the developer Discord asking variations of the same question: \u201cIs AI over?\u201d\nNot \u201cis AI hype slowing down.\u201d Not \u201care we in a correction.\u201d\nIs AI actually dead?\nAnd honestly? I didn\u2019t know. So I did what any paranoid researcher would do \u2014 I started digging.\nWhat I found was\u2026 complicated. Not the answer everyone\u2019s looking for, but probably the one we need to hear.\nThe Timeline (And Why I Started Panicking)\nMonday Dec 15, 8 AM: CoreWeave stock drops 28% in pre-market. $50B company suddenly worth less.\nMonday 9 AM: Oracle announces 60% slower growth than expected. Stock tanks.\nMonday 2 PM: AI infrastructure companies start collapsing across the board. My feed is people saying \u201cAI bubble is bursting.\u201d\nTuesday morning: I\u2019m checking if this is real or just overblown tech media panic.\nBy Tuesday afternoon, I realized neither. It\u2019s worse. Or better. I\u2019m not even sure which.",
    "Score": 0,
    "Date": "2025-12-17",
    "Word_Count": 185,
    "Comments": []
}