{
    "ID": "article_e99c6c17accf30c1",
    "Source": "medium",
    "Type": "Article",
    "Author": "Diwesh Saxena",
    "Title": "Building High-Performance Engineering Teams: 7 Traits That Truly Matter",
    "Text": "Member-only story\nBuilding High-Performance Engineering Teams: 7 Traits That Truly Matter\nOver the past 16 years, as a CTO scaling engineering teams across healthcare, HR tech, and AI-driven platforms, I\u2019ve hired many talented engineers. Early on, I assumed that the best technical skills always created the best teams. But experience has taught me something different:\nTechnical skills get engineers through the door, but mindset, attitude, and adaptability keep them in the room.\nWhen building teams today, here are the seven traits I look for \u2014 traits that consistently differentiate good engineers from truly great ones:\n1. Ownership Mindset\nOwnership isn\u2019t something easily taught. It\u2019s an instinct. It\u2019s the engineer who says, \u201cI\u2019ll fix this,\u201d without hesitation.\nReal-world example: Abhishek, one of our senior engineers, single-handedly brought a patient-monitoring API back online at 2 AM, without waiting for instructions. He treated it as his personal responsibility.\n2. Clear Communication\nClear communication prevents costly misunderstandings and project delays.\nReal-world example: Aditya\u2019s daily three-line update during a global product rollout prevented a week\u2019s worth of potential rework. Clear, concise, and\u2026",
    "Score": 0,
    "Date": "2025-05-23",
    "Word_Count": 177,
    "Comments": []
}